README.md
setup.cfg
setup.py
qppwg/__init__.py
qppwg.egg-info/PKG-INFO
qppwg.egg-info/SOURCES.txt
qppwg.egg-info/dependency_links.txt
qppwg.egg-info/entry_points.txt
qppwg.egg-info/requires.txt
qppwg.egg-info/top_level.txt
qppwg/bin/__init__.py
qppwg/bin/compute_statistics.py
qppwg/bin/decode.py
qppwg/bin/preprocess.py
qppwg/bin/train.py
qppwg/datasets/__init__.py
qppwg/datasets/audio_feat_dataset.py
qppwg/distributed/__init__.py
qppwg/distributed/launch.py
qppwg/layers/__init__.py
qppwg/layers/residual_block.py
qppwg/layers/upsample.py
qppwg/losses/__init__.py
qppwg/losses/stft_loss.py
qppwg/models/__init__.py
qppwg/models/qppwg.py
qppwg/optimizers/__init__.py
qppwg/optimizers/radam.py
qppwg/utils/__init__.py
qppwg/utils/features.py
qppwg/utils/filters.py
qppwg/utils/index.py
qppwg/utils/utils.py