Metadata-Version: 2.1
Name: qppwg
Version: 0.1.2a0
Summary: Quasi-Periodic Parallel WaveGAN implementation
Home-page: http://github.com/bigpon/QPPWG
Author: Yi-Chiao Wu
Author-email: yichiao.wu@g.sp.m.is.nagoya-u.ac.jp
License: MIT License
Platform: UNKNOWN
Classifier: Programming Language :: Python :: 3.6
Classifier: Programming Language :: Python :: 3.7
Classifier: Intended Audience :: Science/Research
Classifier: Operating System :: POSIX :: Linux
Classifier: License :: OSI Approved :: MIT License
Classifier: Topic :: Software Development :: Libraries :: Python Modules
Provides-Extra: test
